pathaccessor/__init__.py
pathaccessor/impl.py
pathaccessor/tests/__init__.py
pathaccessor/tests/test_pathaccessor.py
pathaccessor-0.1.2.dist-info/METADATA
pathaccessor-0.1.2.dist-info/WHEEL
pathaccessor-0.1.2.dist-info/top_level.txt
pathaccessor-0.1.2.dist-info/RECORD
