Metadata-Version: 2.1
Name: pathaccessor
Version: 0.1.2
Summary: Track the key path into a dicts-and-lists data structure.
Home-page: https://github.com/nejucomo/pathaccessor
Author: Nathan Wilcox
Author-email: nejucomo+dev@gmail.com
License: GPLv3
Platform: UNKNOWN
